pytest_check/__init__.py
pytest_check/check_functions.py
pytest_check/check_log.py
pytest_check/check_raises.py
pytest_check/context_manager.py
pytest_check/plugin.py
pytest_check/pseudo_traceback.py
pytest_check/py.typed
pytest_check-2.6.0.dist-info/METADATA
pytest_check-2.6.0.dist-info/WHEEL
pytest_check-2.6.0.dist-info/entry_points.txt
pytest_check-2.6.0.dist-info/licenses/LICENSE.txt
pytest_check-2.6.0.dist-info/RECORD
