Metadata-Version: 2.4
Name: pytest-check
Version: 2.6.0
Summary: A pytest plugin that allows multiple failures per test.
Project-URL: Home, https://github.com/okken/pytest-check
Author: Brian Okken
License: The MIT License (MIT)
License-File: LICENSE.txt
Classifier: Development Status :: 5 - Production/Stable
Classifier: Framework :: Pytest
Classifier: Intended Audience :: Developers
Classifier: Programming Language :: Python
Classifier: Programming Language :: Python :: 3.9
Classifier: Programming Language :: Python :: 3.10
Classifier: Programming Language :: Python :: 3.11
Classifier: Programming Language :: Python :: 3.12
Classifier: Programming Language :: Python :: 3.13
Classifier: Programming Language :: Python :: 3.14
Classifier: Topic :: Software Development :: Testing
Classifier: Topic :: Utilities
Requires-Python: >=3.9
Requires-Dist: pytest>=7.0.0
Requires-Dist: typing-extensions<5,>=4.12.2; python_version < '3.11'
Provides-Extra: dev
Requires-Dist: build; extra == 'dev'
Requires-Dist: tox; extra == 'dev'
Requires-Dist: tox-uv; extra == 'dev'
